wea_display_schema/__init__.py
wea_display_schema/base.py
wea_display_schema/display2d.py
wea_display_schema/display3d.py
wea_display_schema/geometry2d.py
wea_display_schema/geometry3d.py
wea_display_schema/visualization.py
wea_display_schema-1.0.0.dist-info/LICENSE
wea_display_schema-1.0.0.dist-info/METADATA
wea_display_schema-1.0.0.dist-info/WHEEL
wea_display_schema-1.0.0.dist-info/top_level.txt
wea_display_schema-1.0.0.dist-info/RECORD
