Metadata-Version: 2.1
Name: wea-display-schema
Version: 1.0.0
Summary: wea-display Data-Model Objects
Home-page: https://github.com/wea-tools/wea-display-schema
Author: wea Tools
Author-email: info@wea.tools
Classifier: Programming Language :: Python :: 3.7
Classifier: Programming Language :: Python :: 3.10
Classifier: Programming Language :: Python :: Implementation :: CPython
Classifier: Operating System :: OS Independent
License-File: LICENSE
Requires-Dist: pydantic-openapi-helper (>=0.2.10)
